MANIFEST.in
README.rst
VERSION
setup.py
simex/__init__.py
simex.egg-info/PKG-INFO
simex.egg-info/SOURCES.txt
simex.egg-info/dependency_links.txt
simex.egg-info/not-zip-safe
simex.egg-info/top_level.txt